timing_asgi/__init__.py
timing_asgi/integrations/__init__.py
timing_asgi/integrations/starlette.py
timing_asgi/interfaces.py
timing_asgi/middleware.py
timing_asgi/utils.py
timing_asgi-0.3.0.dist-info/WHEEL
timing_asgi-0.3.0.dist-info/METADATA
timing_asgi-0.3.0.dist-info/RECORD
